helloworld/__init__.py
helloworld/core.py
helloworld/web.py
helloworld/templates/index.html
hellonj1902-2.0.2.dist-info/LICENSE
hellonj1902-2.0.2.dist-info/METADATA
hellonj1902-2.0.2.dist-info/WHEEL
hellonj1902-2.0.2.dist-info/entry_points.txt
hellonj1902-2.0.2.dist-info/top_level.txt
hellonj1902-2.0.2.dist-info/RECORD
